wadeTools/111.py
wadeTools/222.py
wadeTools/__init__.py
wadeTools/wadeTool_baiduSearchTools.py
wadeTools/wadeTools_AiSearch.py
wadeTools/wadeTools_Clipboard.py
wadeTools/wadeTools_FindSmallImgInBigImg.py
wadeTools/wadeTools_JDAPI.py
wadeTools/wadeTools_Notice.py
wadeTools/wadeTools_Police.py
wadeTools/wadeTools_Print.py
wadeTools/wadeTools_ReadAndWrite.py
wadeTools/wadeTools_Request.py
wadeTools/wadeTools_SystemAgent.py
wadeTools/wadeTools_Text.py
wadeTools/wadeTools_TkinterClass.py
wadeTools/wadeTools_UserJSON.py
wadeTools/wadeTools_WebTemplateFactory.py
wadeTools/wadeTools_WindowsToolS_CopyPaste.py
wadeTools/wadeTools_aliYunVolice.py
wadeTools/wadeTools_baiduORC.py
wadeTools/wadeTools_baiduPost_API.py
wadeTools/wadeTools_dataoke_API.py
wadeTools/wadeTools_db_Sqlite.py
wadeTools/wadeTools_email.py
wadeTools/wadeTools_encodingTxt.py
wadeTools/wadeTools_error.py
wadeTools/wadeTools_feishu.py
wadeTools/wadeTools_getSystemInfo.py
wadeTools/wadeTools_gol.py
wadeTools/wadeTools_imageTools.py
wadeTools/wadeTools_listFilesName.py
wadeTools/wadeTools_lock.py
wadeTools/wadeTools_log.py
wadeTools/wadeTools_path.py
wadeTools/wadeTools_pyqt5Template.py
wadeTools/wadeTools_readConfig_ini.py
wadeTools/wadeTools_safeBox.py
wadeTools/wadeTools_txt.py
wadeTools/wadeTools_webDriver.py
wadeTools/wadeTools_zuiyou.py
wadeTools/wadeToos_Adb.py
wadeTools/wadeToos_Thread.py
wadeTools/wadeToos_deepseek.py
wadetools-1.0.3.dist-info/METADATA
wadetools-1.0.3.dist-info/WHEEL
wadetools-1.0.3.dist-info/top_level.txt
wadetools-1.0.3.dist-info/RECORD
