Metadata-Version: 2.4
Name: wadeTools
Version: 1.0.3
Summary: 仅包含abc.py的工具包
Home-page: http://www.tbzhu.com
Author: wade
Author-email: 317909531@qq.com
Classifier: Programming Language :: Python :: 3
Requires-Python: >=3.8
Dynamic: author
Dynamic: author-email
Dynamic: home-page
